{
  "provider": "GNews via GitHub Actions",
  "updatedAt": "2026-05-02T05:38:44.566Z",
  "windowLabel": "GitHub Pages 互換版",
  "categories": {
    "general": {
      "jp": [
        {
          "title": "『Apex Legends』シーズン29「オーバークロック」追加の新レジェンド・アクセルはとにかくスピード感が気持ちいい！【先行キャプチャーイベントレポ】",
          "description": "アクセルはスライディングと設置型アビリティで高速移動が可能！敵を逃すな！",
          "url": "https://www.gamespark.jp/article/2026/05/02/165950.html",
          "source": {
            "name": "Game*Spark"
          },
          "publishedAt": "2026-05-01T15:00:05Z",
          "image": "https://www.gamespark.jp/imgs/ogp_f/1123958.png",
          "language": "ja"
        },
        {
          "title": "【5月2日更新】もうすぐ終了のセール情報まとめ！ 「ペルソナ5R」80%オフで約1,500円に",
          "description": "現在、各プラットフォームにてゴールデンウィークに合わせたセールが開催中。その中からセール終了までの期間が短い注目作をピックアップし、紹介していく。",
          "url": "https://game.watch.impress.co.jp/docs/news/2106015.html",
          "source": {
            "name": "GAME Watch"
          },
          "publishedAt": "2026-05-01T15:00:00Z",
          "image": "https://game.watch.impress.co.jp/img/gmw/list/2106/015/000.jpg",
          "language": "ja"
        },
        {
          "title": "錦織圭引退で日本テニス界は分岐点（tennis365.net）｜ｄメニューニュース",
          "description": "錦織圭引退で日本テニス界は分岐点（tennis365.net）錦織圭（2025年） 画像提供:ゲッティイメージズ\n男子テニスで元世界ランク４位の錦織圭は１日に今季限りでの現役引退を発表。長年…",
          "url": "https://topics.smt.docomo.ne.jp/article/tennis365/sports/tennis365-202605_157342?redirect=1",
          "source": {
            "name": "ｄメニューニュース"
          },
          "publishedAt": "2026-05-01T14:34:00Z",
          "image": "https://img.topics.smt.news.goo.ne.jp/picture/tennis365/m_tennis365-202605_157342.jpg",
          "language": "ja"
        },
        {
          "title": "【指揮官一問一答】ヤクルト・池山隆寛監督、サイクル安打の丸山和郁に「もともとは外野のバックアップだったけど…」 自身も1990年に達成",
          "description": "（セ・リーグ、ヤクルト16―5DeNA、6回戦、ヤクルト6勝、1日、神宮）ヤクルトはともに今季最多の20安打、16得点で快勝した。「1番・右翼」で先発出場した丸山和郁外野手（26）が史上73人目、78度目のサイクル安打を達成。「2番・中堅…",
          "url": "https://www.sanspo.com/article/20260501-MYFTZA7LPJL6TN24CNKWQI6KEA/?outputType=theme_swallows",
          "source": {
            "name": "サンスポ"
          },
          "publishedAt": "2026-05-01T13:23:32Z",
          "image": "https://www.sanspo.com/resizer/v2/6LK5VHSUKZNGDDABCESA3J3TUU.jpg?auth=20abee5153da4dbabf685da783a2224f3eb12a82ea4ead8ad6a38ad0e4a7e64f&quality=50&focal=1340%2C1515&width=1200&height=675",
          "language": "ja"
        },
        {
          "title": "【●虎将トーク】阪神・藤川監督、4戦未勝利の今季の村上「悲観することもない」「まあまあっていう感じ」1番岡城の狙い「それは言えない」",
          "description": "（セ・リーグ、阪神3ー5巨人、6回戦、巨人4勝2敗、甲子園）阪神が巨人戦3連敗。中5日登板の村上頌樹投手（27）が二回無死からの連続四球と死球で満塁を招き、平山功太内野手（22）の中前打で2点を献上。三回無死一、二塁ではボビー・ダルベック…",
          "url": "https://www.sanspo.com/article/20260501-DKZMK47BNVLGHFEB35U5AOLB6Y/?outputType=theme_tigers",
          "source": {
            "name": "サンスポ"
          },
          "publishedAt": "2026-05-01T13:02:17Z",
          "image": "https://www.sanspo.com/resizer/v2/WIVU6BFKJFM2VK6BMT7EKRN6ZM.jpg?auth=05deefb12aec24cc13446a784f51f7ad998aca9bbdafd6c7aadc8fcceae117da&quality=50&focal=869%2C494&width=1200&height=675",
          "language": "ja"
        },
        {
          "title": "【巨人】田中将大、黒田博樹に並ぶ歴代２位の日米通算２０３勝 今季無傷の３連勝…“虎キラー”ダルベック、トップタイ７号３ラン 首位・阪神に１・５ゲーム差",
          "description": "◆ＪＥＲＡセ・リーグ　阪神３―５巨人（１日・甲子園）\n　巨人が敵地で阪神に完勝し、甲子園では今季３戦３勝とした。先発の田中将大投手が６回途中３失点と試合をつくり、黒田博樹に並ぶ歴代２位の日米通算２",
          "url": "https://news.yahoo.co.jp/articles/480bbbe188b13192a91ac77c63e10ad7a2d05566",
          "source": {
            "name": "Yahoo!ニュース"
          },
          "publishedAt": "2026-05-01T12:33:55Z",
          "image": "https://newsatcl-pctr.c.yimg.jp/t/amd-img/20260501-05011369-sph-000-2-view.jpg?exp=10800",
          "language": "ja"
        },
        {
          "title": "福生市“ハンマー殴打”男を逮捕 母親「安心した」 習志野市のアパートに…居住者との関係性わからず",
          "description": "東京都福生市で、ハンマーで少年を殴るなどし、逃走していた男が1日午後、殺人未遂の疑いで逮捕されました。逮捕を受けて、母親が取材に応じました。",
          "url": "https://news.ntv.co.jp/category/society/29dda234a55b49ff978a075a2ffd6c55",
          "source": {
            "name": "日テレNEWS NNN"
          },
          "publishedAt": "2026-05-01T12:30:01Z",
          "image": "https://news.ntv.co.jp/gimage/n24/articles/2cb5dfa7d2e34a54a0913f61fb0c87fa/20260501-175935-099-ch03-09-5376f1a8-1.jpg?w=1200",
          "language": "ja"
        },
        {
          "title": "映画『プラダを着た悪魔2』キャストのファッション解説、人気ブランドを着こなす主演2人の衣装",
          "description": "おしゃれ好きにも、映画好きにも支持される映画『プラダを着た悪魔』。2006年に公開された同作は、ファッション業界を牽引するトップ誌『ランウェイ』に就職したアンドレア(アンディ)・サックスが、カリスマ編...",
          "url": "https://www.fashion-press.net/news/146001",
          "source": {
            "name": "ファッションプレス"
          },
          "publishedAt": "2026-05-01T12:00:00Z",
          "image": "https://www.fashion-press.net/img/news/146001/top.jpg?1777482737",
          "language": "ja"
        },
        {
          "title": "シームレスに聴き倒せる！極上「オープンイヤータイプイヤホン」7選【大人のための最新オーディオ大全】|au Webポータル",
          "description": "【大人のための最新オーディオ大全】 ながら聴き需要や安全性志向、フィットネスブームが重なって急成長しているオープンイヤータイプイヤホン。e☆イヤホンのゆーでぃさんは「ユーザーが重視しているのは、装着感",
          "url": "https://article.auone.jp/detail/1/3/7/177_7_r_20260501_1777636995137625",
          "source": {
            "name": "au Webポータル"
          },
          "publishedAt": "2026-05-01T12:00:00Z",
          "image": "https://portal.st-img.jp/thumb/4909bafa67a0ea11b11d97892d5708de_1777636995_l.jpg",
          "language": "ja"
        },
        {
          "title": "為替介入、原油高主導の円安問題視 連休前の薄商い狙った政府・日銀",
          "description": "政府・日銀は円買い介入に踏み切った。原油価格の高騰をきっかけにした一方的な円安を食い止めるのが狙いだ。中東情勢は緊迫が続き、日米金利差など経済環境に変化はない。介入で円安トレンドが変わるとの見方は乏しい。あらためて円売りの動きをけん制「大型連休はまだまだ序盤だ」1年9カ月ぶりの円買い介入から一晩明けた1日朝、財務省に登庁した三村淳財務官は集まった記者団にこう告げた。介入の有無には言及しなか",
          "url": "https://www.nikkei.com/article/DGXZQOUA011U60R00C26A5000000/",
          "source": {
            "name": "日本経済新聞"
          },
          "publishedAt": "2026-05-01T10:28:25Z",
          "image": "https://article-image-ix.nikkei.com/https%3A%2F%2Fimgix-proxy.n8s.jp%2FDSXZQO2972271001052026000000-1.jpg?auto=compress&bg=FFFF&crop=focalpoint&fit=crop&fm=jpg&fp-x=0.59&fp-y=0.26&h=630&w=1200&s=b12ef9e11e59bf4f55d4dbeeec79c5b4",
          "language": "ja"
        }
      ],
      "world": [
        {
          "title": "CKM Syndrome Linked to Cancer. How to Lower Your Risk",
          "description": "People with cardiovascular-kidney-metabolic (CKM) syndrome have a higher risk of developing cancer, according to a new study. Experts say that adopting healthy lifestyle habits can help offer some protection.",
          "url": "https://www.healthline.com/health-news/ckm-syndrome-higher-cancer-risk",
          "source": {
            "name": "Healthline"
          },
          "publishedAt": "2026-05-01T17:33:40Z",
          "image": "https://media.post.rvohealth.io/wp-content/uploads/2026/05/Cardiovascular-Disease-Stocksy_txp00d01d6cWvG400_Medium_308410-Facebook.jpg",
          "language": "en"
        },
        {
          "title": "Arsenal line-up vs Fulham decided as Myles Lewis-Skelly unleashed in new role",
          "description": "football.london reporters select their Arsenal starting XIs for the Premier League clash against Fulham",
          "url": "https://www.football.london/arsenal-fc/news/arsenal-lineup-fulham-injury-news-33874281",
          "source": {
            "name": "Football London"
          },
          "publishedAt": "2026-05-01T17:33:28Z",
          "image": "https://i2-prod.football.london/article33874268.ece/ALTERNATES/s1200d/0_GettyImages-2253605905.jpg",
          "language": "en"
        },
        {
          "title": "Devil Wears Prada 2 And More",
          "description": "This week in TV and movie news, “The Devil Wears Prada 2” is worth a watch, why one of the best shows right now is a time travel series on Hallmark, and much more.",
          "url": "https://www.buzzfeed.com/noradominick/weekend-tv-movie-recommendations-5-1-26",
          "source": {
            "name": "BuzzFeed"
          },
          "publishedAt": "2026-05-01T17:31:02Z",
          "image": "https://img.buzzfeed.com/buzzfeed-static/static/2026-04/30/03/thumb/BsE90Wz5s.jpg?crop=1250:654;0,0%26downsize=1250:*",
          "language": "en"
        },
        {
          "title": "Charles tamed Trump while rebuking Trumpism in ego-flattering masterstroke",
          "description": "King skillfully appeals to Republicans fond of Britain and Democrats anxious about rules-based order in state visit",
          "url": "https://www.theguardian.com/us-news/2026/may/01/king-charles-trump-visit",
          "source": {
            "name": "The Guardian"
          },
          "publishedAt": "2026-05-01T17:31:00Z",
          "image": "https://i.guim.co.uk/img/media/22d5f15cf2c1c98c28d414f901876a3175d16e3a/209_0_2091_1673/master/2091.jpg?width=1200&height=630&quality=85&auto=format&fit=crop&precrop=40:21,offset-x50,offset-y0&overlay-align=bottom%2Cleft&overlay-width=100p&overlay-base64=L2ltZy9zdGF0aWMvb3ZlcmxheXMvdGctZGVmYXVsdC5wbmc&enable=upscale&s=d684dfb2a9f55fd6102a09c0e3e8bb80",
          "language": "en"
        },
        {
          "title": "UEFA Women's Europa Cup final winners: Häcken",
          "description": "Follow all the latest UEFA Women's Europa Cup 2025/2026 news from the official UEFA.com site. Includes latest news stories, videos, match reports and much more.",
          "url": "https://www.uefa.com/womenseuropacup/news/02a4-204b8a43563f-ac4405dde37d-1000--uefa-women-s-europa-cup-final-winners-hacken/",
          "source": {
            "name": "UEFA.com"
          },
          "publishedAt": "2026-05-01T17:30:44Z",
          "image": "https://editorial.uefa.com/resources/02a5-2085a77679bd-1e0acf882b6b-1000/hammarby_if_v_bk_hacken_ff_-_uefa_women_s_europa_cup_2026_final_second_leg.jpeg",
          "language": "en"
        },
        {
          "title": "Sourav Ganguly on Bengal poll outcome: 'Even Ma Durga ...'",
          "description": "Majority of exit poll predictions suggest that the Bharatiya Janata Party (BJP) has an edge over the ruling TMC. However, Today's Chanakya has predicted a massive win for BJP, predicting a tally of 192+ for the saffron party.",
          "url": "https://www.moneycontrol.com/europe/?url=https://www.moneycontrol.com/elections/assembly-election/west-bengal/sourav-ganguly-on-bengal-poll-outcome-even-ma-durga-article-13905656.html",
          "source": {
            "name": "Moneycontrol.com"
          },
          "publishedAt": "2026-05-01T17:30:23Z",
          "image": "https://images.moneycontrol.com/static-mcnews/2026/05/20260501153652_Ganguly.jpg",
          "language": "en"
        },
        {
          "title": "KeNHA outlines steps towards reconstruction of Nithi Bridge",
          "description": "The redesign and realignment of the bridge is expected to promote safety and stability.",
          "url": "https://www.the-star.co.ke/news/2026-05-01-kenha-outlines-nithi-bridge-rebuild-plan",
          "source": {
            "name": "the-star.co.ke"
          },
          "publishedAt": "2026-05-01T17:28:26Z",
          "image": "https://cdn.radioafrica.digital/image/2026/05/e168a173-597c-44fe-81cf-fdd120cb0d30.jpg?1777667777192",
          "language": "en"
        },
        {
          "title": "Here's Where Your Backyard Was 300 Million Years Ago",
          "description": "We may use terms like \"grounded\" and terra firma to mean stability and consistency but geology laughs at that notion.",
          "url": "http://www.science20.com/news_staff/heres_where_your_backyard_was_300_million_years_ago-257763",
          "source": {
            "name": "Science 2.0"
          },
          "publishedAt": "2026-05-01T17:26:19Z",
          "image": "https://www.science20.com/files/images/paleolatitude.png",
          "language": "en"
        },
        {
          "title": "Nigerians and Ghanaians convicted in US: Department of Justice release names of Nigerians, Ghanaians, odas wey dem convict for $215m scam",
          "description": "Out of di 25 defendants, some of dem na Nigerians and Ghanaians and plenti US citizens dey among dem wey plead guilty say dem do di fraud.",
          "url": "https://www.bbc.com/pidgin/articles/cp8p1yn83gro",
          "source": {
            "name": "BBC"
          },
          "publishedAt": "2026-05-01T17:25:55Z",
          "image": "https://ichef.bbci.co.uk/news/1024/branded_pidgin/a644/live/ea5fe390-457c-11f1-806d-8d4b5ff877ff.png",
          "language": "en"
        },
        {
          "title": "Retire? New AC Milan Deal? Luka Modrić's Big Decision As World Cup Looms",
          "description": "Luka Modric is facing a major decision about his future as he prepares to lead Croatia at the World Cup.",
          "url": "https://www.foxsports.com/stories/soccer/new-contract-or-retire-luka-modric-future-prediction-made-at-40-years-of-age-with-ballon-dor-winning-real-madrid-legend-nursing-an-injury-at-ac-milan",
          "source": {
            "name": "FOX Sports"
          },
          "publishedAt": "2026-05-01T17:23:43Z",
          "image": "https://a57.foxsports.com/statics.foxsports.com/www.foxsports.com/content/uploads/2026/05/1408/814/FotoJet20-202026-03-09T074203.821.jpg?ve=1&tl=1",
          "language": "en"
        }
      ]
    }
  }
}
