{
  "provider": "GNews via GitHub Actions",
  "updatedAt": "2026-06-17T04:16:20.920Z",
  "windowLabel": "GitHub Pages 互換版",
  "categories": {
    "general": {
      "jp": [
        {
          "title": "『THE MUSIC DAY 2026』第2弾出演アーティストにあいみょん、timeleszら 番組特別企画も発表",
          "description": "7月4日13時30分より放送される音楽特番『THE MUSIC DAY 2026』（日本テレビ系）の、第2弾出演アーティストが発表となった。　今回は、INI、あいみょん、＝LOVE、&TEAM、海援隊、かりゆし58、King & Prince、Snow Man、timel…",
          "url": "https://realsound.jp/2026/06/post-2429714.html",
          "source": {
            "name": "Real Sound｜リアルサウンド"
          },
          "publishedAt": "2026-06-16T15:54:02Z",
          "image": "https://realsound.jp/wp-content/uploads/2026/06/20260616-musicday-99.jpeg",
          "language": "ja"
        },
        {
          "title": "実はすごい快挙。原子の粒が自由に動く様子の撮影に成功",
          "description": "2025年5月19日の記事を編集して再掲載しています。物理と聞くと、難しそうって思いませんか？少なくとも私は難しそうな印象を抱いています。だから選択科目で物理か生物かを選ぶときに、迷わず生物を選択したんです。だって生物の方が眼に見えるものが",
          "url": "https://www.gizmodo.jp/article/photographing-moving-atoms-ycz/",
          "source": {
            "name": "Gizmodo"
          },
          "publishedAt": "2026-06-16T14:00:00Z",
          "image": "https://media.loom-app.com/gizmodo/dist/images/2025/05/19/MIT-FreeAtoms-01-press.jpg?w=1200&h=630",
          "language": "ja"
        },
        {
          "title": "【情報まとめ】埼玉北部・群馬南部で震度5弱 津波の心配なし",
          "description": "気象庁は茨城県南部で発生した地震について、1週間程度は最大震度5弱程度の地震に注意するよう呼びかけました。16日午後7時半過ぎ茨城県南部で深さ50キロを震源とするマグニチュード5.5の地震が発生し、群",
          "url": "https://news.tv-asahi.co.jp/news_society/articles/900193023.html",
          "source": {
            "name": "テレ朝NEWS"
          },
          "publishedAt": "2026-06-16T13:45:00Z",
          "image": "https://news.tv-asahi.co.jp/articles_img/900193023_1200.jpg",
          "language": "ja"
        },
        {
          "title": "Googleも挫折した「血糖値ガジェット」の難しさ",
          "description": "血糖値が測れるコンタクトレンズを開発します！とGoogleが発表して早10余年。実現すれば世界3億8000万人の糖尿病患者の生活が変わるのみにならず、ウェアラブル業界全体のブレイクスルーになる！ Googleみたいな大手テック会社が医療機器",
          "url": "https://www.gizmodo.jp/article/why-noninvasive-blood-glucose-monitoring-is-still-the-holy-grail-of-wearables/",
          "source": {
            "name": "Gizmodo"
          },
          "publishedAt": "2026-06-16T13:30:00Z",
          "image": "https://media.loom-app.com/loom/2026/05/30/c29eee76-03aa-4dbd-9008-627c30d391a0/original.png?w=1200&h=630",
          "language": "ja"
        },
        {
          "title": "武内夏暉が6回10K＆桑原将志は決勝打！ 埼玉西武が交流戦初優勝決める",
          "description": "試合戦評｜　6月16日、甲子園で行われた阪神と埼玉西武の「日本生命セ・パ交流戦 2026」第3回戦は、1対0で埼玉西武が勝利。14勝3敗1分の勝率.824で球団史上初の交流戦優勝を決めた。　先発は武内夏暉投手。初回から得点圏に走…",
          "url": "https://pacificleague.com/news/2026/6/83794",
          "source": {
            "name": "パ・リーグ.com"
          },
          "publishedAt": "2026-06-16T13:16:21Z",
          "image": "https://media.insight.pacificleague.com/webp/jhshWjRWm2dBSZyaEgj8Zst9HUjyAljZI02mVzkW.webp",
          "language": "ja"
        },
        {
          "title": "ASUS「ROG Xbox Ally X」、20周年記念で画面がちょい大きくなった。ハード面もパワーアップ",
          "description": "ASUS（エイスース）のゲーミングブランドであるROGが今年で20周年となります。それを記念してポータブルゲーム機「ROG Xbox Ally X」の特別モデル「ROG Xbox Ally X20」が",
          "url": "https://article.auone.jp/detail/1/3/7/32_7_r_20260616_1781615846907429",
          "source": {
            "name": "au Webポータル"
          },
          "publishedAt": "2026-06-16T12:30:00Z",
          "image": "https://portal.st-img.jp/thumb/b516809458bec8457f0eff50087f62f4_1781615846_l.jpg",
          "language": "ja"
        },
        {
          "title": "ASUS「ROG Xbox Ally X」、20周年記念で画面がちょい大きくなった。ハード面もパワーアップ",
          "description": "ASUS（エイスース）のゲーミングブランドであるROGが今年で20周年となります。それを記念してポータブルゲーム機「ROG Xbox Ally X」の特別モデル「ROG Xbox Ally X20」が発表されました。このROG Xbox A",
          "url": "https://www.gizmodo.jp/article/asus-just-gave-the-xbox-ally-x-a-huge-screen-upgrade-but-theres-a-catch/",
          "source": {
            "name": "Gizmodo"
          },
          "publishedAt": "2026-06-16T12:30:00Z",
          "image": "https://media.loom-app.com/loom/2026/06/03/3b095df7-0adf-4228-93fb-781968cb5b35/original.jpg?w=1200&h=630",
          "language": "ja"
        },
        {
          "title": "スペイン封じたカーボベルデ代表DFは異色の経歴…元住宅ローンアドバイザー、招集オファーをスパムと勘違いして無視",
          "description": "カーボベルデ代表DFピコは異色の経歴を持つ選手のようだ。『BBC』は「ハリウッドの脚本家でさえあり得ない話だと考えるかもしれない」と伝えている。　ピコはカーボベルデのW杯デビュー戦となったスペイン戦で...",
          "url": "https://web.gekisaka.jp/news/worldcup/detail/?453551-453551-fl",
          "source": {
            "name": "gekisaka.jp"
          },
          "publishedAt": "2026-06-16T12:21:00Z",
          "image": "https://f.image.geki.jp/data/image/news/2560/454000/453551/news_453551_1.jpg?time=20260616212742",
          "language": "ja"
        },
        {
          "title": "死にゆく「炭素星」の化学組成",
          "description": "全天で最も明るい炭素星「しし座CW星」と2番目に明るい「CIT 6」の観測データの比較から、炭素星の分子形成プロセスに共通性があり、中心星の紫外線により分子存在量が抑えられることなどがわかった",
          "url": "https://www.astroarts.co.jp/article/hl/a/14536_carbonstar",
          "source": {
            "name": "astroarts.co.jp"
          },
          "publishedAt": "2026-06-16T11:08:45Z",
          "image": "https://www.astroarts.co.jp/article/attachment/53930/key_visual.jpg",
          "language": "ja"
        },
        {
          "title": "「ABCお笑いグランプリ」決勝で新ルール導入 ネタ順も決定、トップバッターはエグい速さ",
          "description": "「第47回ABCお笑いグランプリ2026」決勝のファーストステージで新ルール「ノックアウト・サバイバル」が導入されることがABEMAの生配信番組「第47回ABCお笑いグランプリ2026 ～決勝進出者生発表スペシャル～」で発表された。",
          "url": "https://natalie.mu/owarai/news/676442",
          "source": {
            "name": "ナタリー"
          },
          "publishedAt": "2026-06-16T09:52:00Z",
          "image": "https://ogre.natalie.mu/media/news/owarai/2026/0528/ABCowaraiGP_2026_logo.jpg?impolicy=twitter_card_face_crop",
          "language": "ja"
        }
      ],
      "world": [
        {
          "title": "Katie Price's hubby Lee Andrews claims he was 'captured at gunpoint' & 'slapped around' for SPYING before she saved him",
          "description": "KATIE Price's husband Lee Andrews has broken his social media silence since going missing weeks ago.\nThe 43-year-old has claimed he was...",
          "url": "https://www.thesun.co.uk/tvandshowbiz/39435023/katie-price-husband-lee-andrews-gunpoint-spy/",
          "source": {
            "name": "The Sun"
          },
          "publishedAt": "2026-06-16T16:16:00Z",
          "image": "https://www.thesun.co.uk/wp-content/uploads/2026/06/newspress-collage-61d1ghc5v-1781626299516.jpg?quality=90&strip=all&1781629915&w=1920&h=1080&crop=1",
          "language": "en"
        },
        {
          "title": "Artists lift the lid on Cork treasure trove at Fota House",
          "description": "Containers, boxes, trunks and suitcases have opened up ideas for a summer display with a difference, writes Eve Kelliher",
          "url": "https://www.irishexaminer.com/property/homeandgardens/arid-41863824.html",
          "source": {
            "name": "Irish Examiner"
          },
          "publishedAt": "2026-06-16T16:16:00Z",
          "image": "https://www.irishexaminer.com/cms_media/module_img/10242/5121276_7_org_Fota-artist-2.jpg",
          "language": "en"
        },
        {
          "title": "After 10 years of MAID, key report on mental illness expansion nears",
          "description": "The extension is set to happen in March 2027, after it was delayed three times by the previous Liberal government, the last time being in February 2024.",
          "url": "https://globalnews.ca/news/11904766/medical-assistance-in-dying-mental-illness/",
          "source": {
            "name": "Global News"
          },
          "publishedAt": "2026-06-16T16:15:59Z",
          "image": "https://globalnews.ca/wp-content/uploads/2026/06/CP173433610.jpg?quality=65&strip=all&w=720&h=379&crop=1",
          "language": "en"
        },
        {
          "title": "Extreme cold, rainy weather expected",
          "description": "TEMPERATURES in the south are expected to drop significantly, with snowfall predicted in some southern areas on Wednesday.",
          "url": "https://informante.web.na/?p=396202",
          "source": {
            "name": "Informanté"
          },
          "publishedAt": "2026-06-16T16:15:00Z",
          "image": "https://informante.web.na/wp-content/uploads/2026/06/Rain-frost-and-snow-expected-Informante-Image-workspace-1024x677.jpg",
          "language": "en"
        },
        {
          "title": "Stolen felines reunited with owners after Vietnam cat-meat bust",
          "description": "HANOI — More than 40 abducted cats have been reunited with owners after Vietnamese police busted a feline theft ring and rescued 400 pets destined to be slaughtered for food, an animal rights group said on Tuesday.",
          "url": "https://www.manilatimes.net/2026/06/17/world/asia-oceania/stolen-felines-reunited-with-owners-after-vietnam-cat-meat-bust/2366931",
          "source": {
            "name": "The Manila Times"
          },
          "publishedAt": "2026-06-16T16:13:00Z",
          "image": "https://manilatimes.net/manilatimes/uploads/images/2026/06/17/1101608.jpg",
          "language": "en"
        },
        {
          "title": "Tom Holland explains why Lamine Yamal 'would make a great Spider-Man' as Hollywood actor assesses Spain's World Cup chances",
          "description": "Tom Holland backs Barcelona star Lamine Yamal as a future Spider-Man while discussing Spain's 2026 World Cup campaign and Julian Alvarez.",
          "url": "https://www.goal.com/en-ug/lists/tom-holland-lamine-yamal-spider-man-hollywood-spain-world-cup/blt4bfabd6e0096e712",
          "source": {
            "name": "Goal.com"
          },
          "publishedAt": "2026-06-16T16:11:38Z",
          "image": "https://assets.goal.com/images/v3/getty-2281744175/crop/MM5DINBUHA5DENJQGI5G433XMU5DAORQ/GettyImages-2281744175.jpg",
          "language": "en"
        },
        {
          "title": "Morgan Rogers has made his transfer feelings crystal clear amid Arsenal interest",
          "description": "Morgan Rogers' comments have offered a glimpse into where he sees himself playing in the future",
          "url": "https://www.football.london/arsenal-fc/transfer-news/morgan-rogers-arsenal-united-transfer-34123518",
          "source": {
            "name": "Football London"
          },
          "publishedAt": "2026-06-16T16:11:13Z",
          "image": "https://i2-prod.football.london/article34094702.ece/ALTERNATES/s1200d/1_Morgan-Rogers.jpg",
          "language": "en"
        },
        {
          "title": "Gatchalian urges all senators to attend special session",
          "description": "ACTING Senate President and Senate President Pro Tempore Sherwin Gatchalian on Tuesday called on all senators to attend the special session scheduled for June 17, emphasizing the need to pass pending measures and confirm the appointments of five military generals whose confirmations have been delayed.",
          "url": "https://www.manilatimes.net/2026/06/17/news/national/gatchalian-urges-all-senators-to-attend-special-session/2366955",
          "source": {
            "name": "The Manila Times"
          },
          "publishedAt": "2026-06-16T16:11:00Z",
          "image": "https://manilatimes.net/manilatimes/uploads/images/2026/06/17/1101934.jpg",
          "language": "en"
        },
        {
          "title": "CBC will no longer show NHL games as sublicense with rights-holder Rogers Sportsnet ends",
          "description": "The NHL will no longer be shown on CBC after it and national rights-holder Rogers Sportsnet were unable to come to agreement on a new sublicensing deal that would have allowed the public broadcaster to air games on its Saturday program Hockey Night in Canada.",
          "url": "https://www.cbc.ca/sports/cbc-nhl-hockey-night-in-canada-ends-9.7236977",
          "source": {
            "name": "CBC"
          },
          "publishedAt": "2026-06-16T16:10:57Z",
          "image": "https://i.cbc.ca/ais/1.6273542,1681495458000/full/max/0/default.jpg?im=Crop%2Crect%3D%280%2C0%2C1080%2C607%29%3BResize%3D620",
          "language": "en"
        },
        {
          "title": "Scientists and decision-makers to discuss Estonia's readiness for climate change",
          "description": "TALLINN - A climate seminar is being held on Tuesday in Tallinn, both at the Tamme hall of the joint ministry building and online, bringing toge...",
          "url": "https://www.baltictimes.com/scientists_and_decision-makers_to_discuss_estonia_s_readiness_for_climate_change/",
          "source": {
            "name": "The Baltic Times"
          },
          "publishedAt": "2026-06-16T16:10:37Z",
          "image": "https://media.baltictimes.com/media/photos/167821_12375229806a31752a00461_big.jpg",
          "language": "en"
        }
      ]
    }
  }
}
