{
  "provider": "GNews via GitHub Actions",
  "updatedAt": "2026-07-10T22:04:35.106Z",
  "windowLabel": "GitHub Pages 互換版",
  "categories": {
    "general": {
      "jp": [
        {
          "title": "フジ月9「恋愛もの」企画変更報道…佐藤二朗・橋本愛ハラスメント騒動の “飛び火” に「過剰反応しすぎちゃう？」SNS呆れ",
          "description": "フジ月9「恋愛もの」企画変更報道…佐藤二朗・橋本愛ハラスメント騒動の “飛び火” に「過剰反応しすぎちゃう？」SNS呆れ（SmartFLASH） \n　佐藤二朗と橋本愛のハラスメント騒動が、フジテレビの看板だった“月9ドラマ”を揺らしている。\n \n「10日配信の『ス…",
          "url": "https://topics.smt.docomo.ne.jp/article/smartflash/entertainment/smartflash-418196?redirect=1",
          "source": {
            "name": "ｄメニューニュース"
          },
          "publishedAt": "2026-07-10T09:40:00Z",
          "image": "https://img.topics.smt.news.goo.ne.jp/picture/smartflash/m_smartflash-418196.jpg",
          "language": "ja"
        },
        {
          "title": "ASCII.jp：「スターオーシャン」シリーズ30周年記念の公式生放送が7月19日に配信決定！",
          "description": "ASCII.jp － ゲーム",
          "url": "https://ascii.jp/elem/000/004/418/4418576/",
          "source": {
            "name": "ASCII.jp"
          },
          "publishedAt": "2026-07-10T09:00:00Z",
          "image": "https://ascii.jp/img/2026/07/10/4498746/xl/0a5087b97fbc546b.jpg?20200122",
          "language": "ja"
        },
        {
          "title": "10代の黒人男性、白人の友人たちと出かけ遺体で発見 事件性なしとの発表に疑念高まる 米",
          "description": "ノーラン・ウェルズさん（18）は4日、米ミシシッピ州のメキシコ湾沖にある人気の砂州島、ホーン島に出かけた。独立記念日を祝うためだった。 - (1/2)",
          "url": "https://www.cnn.co.jp/usa/35250449.html",
          "source": {
            "name": "CNN.co.jp"
          },
          "publishedAt": "2026-07-10T08:42:00Z",
          "image": "https://www.cnn.co.jp/storage/2026/07/10/ec845c4073b8497c39752825b82f5c5e/nolan-wells-from-jackson-county.jpg",
          "language": "ja"
        },
        {
          "title": "『パルワールド』正式版1.0が本日（7/10）発売。新種パル72種、天陽郷や世界樹といった新エリアなど、新要素が大量追加。過去最安値の30％オフセールも実施中",
          "description": "『パルワールド』正式版“1.0”が2026年7月10日に配信開始。新エリアや新育成要素についてのパッチノートが公開。Steam などで過去最安値となる30%オフセールが実施中。",
          "url": "https://www.famitsu.com/article/202607/81000",
          "source": {
            "name": "ファミ通"
          },
          "publishedAt": "2026-07-10T08:40:00Z",
          "image": "https://cimg.kgl-systems.io/camion/files/81000/thumbnail_yMcO.jpg?x=1280",
          "language": "ja"
        },
        {
          "title": "『アサシン クリード ブラック フラッグ RE:シンクロ』発売1日後“賛否両論”スタート。多数の少額課金DLCと中国からのレビュー爆撃など原因か",
          "description": "『アサシン クリード ブラック フラッグ RE:シンクロ』、順風満帆の船出とはいかず？",
          "url": "https://www.gamespark.jp/article/2026/07/10/169105.html",
          "source": {
            "name": "Game*Spark"
          },
          "publishedAt": "2026-07-10T08:35:02Z",
          "image": "https://www.gamespark.jp/imgs/ogp_f/1157463.jpg",
          "language": "ja"
        },
        {
          "title": "『スターオーシャン』30周年当日の7月19日に記念生放送。「#ここが好きだよスターオーシャン」キャンペーンも開催中",
          "description": "『セカンドストーリー R』開発元ジェムドロップの北尾雄一郎さんらが出演。なお、シリーズ新作ゲームの情報はないとのこと",
          "url": "https://news.denfaminicogamer.jp/news/2607102o",
          "source": {
            "name": "電ファミニコゲーマー"
          },
          "publishedAt": "2026-07-10T08:03:00Z",
          "image": "https://news.denfaminicogamer.jp/wp-content/uploads/2026/07/f854f881b05e58e7b3db4fd0cfc3cb79.jpg",
          "language": "ja"
        },
        {
          "title": "【↑】日経平均 大引け｜ 続伸、AI・半導体関連中心に買いが流入 (7月10日)",
          "description": "前日の米国市場では、ＮＹダウは前日比１３９ドル高と３日ぶりに反発した。対イラン和平協議の再開期待や原油安を受け、ハイテク株を中心に買いが優勢となった。　東京市場では、日経平均株価は続伸。前日の米株高を受けＡＩ・半導体関連株などに買いが流入した・・・。",
          "url": "https://kabutan.jp/news/marketnews/?b=n202607100970",
          "source": {
            "name": "株探"
          },
          "publishedAt": "2026-07-10T07:29:37Z",
          "image": "https://async.api.kabutan.jp/og_image?title=%E3%80%90%E2%86%91%E3%80%91%E6%97%A5%E7%B5%8C%E5%B9%B3%E5%9D%87%20%E5%A4%A7%E5%BC%95%E3%81%91%EF%BD%9C%20%E7%B6%9A%E4%BC%B8%E3%80%81AI%E3%83%BB%E5%8D%8A%E5%B0%8E%E4%BD%93%E9%96%A2%E9%80%A3%E4%B8%AD%E5%BF%83%E3%81%AB%E8%B2%B7%E3%81%84%E3%81%8C%E6%B5%81%E5%85%A5%20%287%E6%9C%8810%E6%97%A5%29",
          "language": "ja"
        },
        {
          "title": "反町隆史『GTO』続編の実現は「相当時間がかかった。もうダメかなと思った時も」ファンと握手を交わし、万感の思いを語る",
          "description": "反町隆史さん主演のドラマ『GTO』の第1話試写会と制作発表会が7月10日に行われ、反町さん、生見愛瑠さん、高橋メアリージュンさんらが登壇しました。“28年ぶりの連続ドラマ復活”と話題の『GTO』は、藤沢とおるさんによる同名漫画が原作（講談社『週刊少年マガジンKC』刊）で、元暴走族の教師・鬼塚英吉（反町）が、型破りな行動で生徒や学校の問題に体当たりでぶつかっていく学園ドラマです。反町隆史さん主演のドラマ『GTO』の第1話試写会と制作発表会が7月10日に行われ、反町さん、生見愛瑠さん、高橋メアリージュンさんらが登壇しました。今回、このイベントの司会を、98年版に続き2026年版にも出演する山崎裕…",
          "url": "https://mezamashi.media/articles/-/319957",
          "source": {
            "name": "めざましmedia"
          },
          "publishedAt": "2026-07-10T07:20:00Z",
          "image": "https://mezamashi.ismcdn.jp/mwimgs/e/2/1200xm/img_e28bbbc1cd49c3c0c80b38d0f66ba723503937.jpg",
          "language": "ja"
        },
        {
          "title": "【速報】江崎グリコが169品目値上げへ 看板商品ビスコなどの菓子類やプッチンプリン、セブンティーンアイスなども対象",
          "description": "【速報】江崎グリコが169品目値上げへ　看板商品ビスコなどの菓子類やプッチンプリン、セブンティーンアイスなども対象（読売テレビニュース）　江崎グリコは、主力商品「ビスコ」など169品目を今年10月1日の出荷分から順次値上げすると発表しました。　江崎グリコによりま…",
          "url": "https://topics.smt.docomo.ne.jp/article/ytv/business/ytv-2026071002977437?redirect=1",
          "source": {
            "name": "ｄメニューニュース"
          },
          "publishedAt": "2026-07-10T06:53:00Z",
          "image": "https://img.topics.smt.news.goo.ne.jp/picture/ytv/m_ytv-2026071002977437.jpg",
          "language": "ja"
        },
        {
          "title": "今春から続いているエルニーニョ現象は今後秋にかけて続く 7月10日発表の監視速報",
          "description": "気象庁は今日7月10日「エルニーニョ監視速報」を発表しました。エルニーニョ現象はこの春から続いているとみられ、今後、秋にかけてエルニーニョ現象が続く見込みです。",
          "url": "https://tenki.jp/forecaster/deskpart/2026/07/10/39675.html",
          "source": {
            "name": "tenki.jp"
          },
          "publishedAt": "2026-07-10T06:04:26Z",
          "image": "https://storage.tenki.jp/storage/static-images/forecaster_diary/image/3/39/396/39675/main/20260710144012/large.jpg",
          "language": "ja"
        }
      ],
      "world": [
        {
          "title": "NL Federation of Labour Calling for Increased Pay for Injured Workers",
          "description": "The Newfoundland and Labrador Federation of Labour says now is the time to give people who are unable to work ...",
          "url": "https://vocm.com/2026/07/10/nl-federation-of-labour-calling-for-increased-pay-for-injured-workers/",
          "source": {
            "name": "VOCM"
          },
          "publishedAt": "2026-07-10T10:04:00Z",
          "image": "https://media-cdn.socastsrm.com/wordpress/wp-content/blogs.dir/900/files/2023/10/jessica-mccormick-federation-of-labour.jpg",
          "language": "en"
        },
        {
          "title": "Prince Harry has Alison Hammond in hysterics in surprise This Morning appearance",
          "description": "Prince Harry and This Morning host Alison Hammond play laser tag at Birmingham Invictus Games event before hugging and laughing.",
          "url": "https://metro.co.uk/2026/07/10/prince-harry-alison-hammond-hysterics-surprise-this-morning-appearance-29101001/",
          "source": {
            "name": "Metro.co.uk"
          },
          "publishedAt": "2026-07-10T10:04:00Z",
          "image": "https://metro.co.uk/wp-content/uploads/2026/07/SEI_304745974-085d_1783680642.jpg?quality=90&strip=all&w=1200&h=630&crop=1",
          "language": "en"
        },
        {
          "title": "2 Cebuanos hospitalized due to Kanlaon ashfall",
          "description": "CEBU CITY – The Cebu provincial government recorded two cases of ashfall-related hospital admissions amid the persisting poor air quality caused by the...",
          "url": "https://mb.com.ph/2026/07/10/2-cebuanos-hospitalized-due-to-kanlaon-ashfall",
          "source": {
            "name": "Manila Bulletin"
          },
          "publishedAt": "2026-07-10T10:03:54Z",
          "image": "https://mb.com.ph/manilabulletin/uploads/images/2026/07/10/115211.webp",
          "language": "en"
        },
        {
          "title": "WHO Official: Congo Ebola Outbreak Still Spreading Largely Undetected",
          "description": "Four out of every five new Ebola cases in parts of Democratic Republic of Congo have no known link to existing patients, a senior World Health Organization official said, warning that the true scale of the outbreak could be two to four times larger than official data suggest. The figures underscore the challenges facing health workers as they battle to contain the outbreak in the country's northeast, which has so far infected 1,792 people and killed 625, according to government data released on Thursday.",
          "url": "https://english.aawsat.com/world/5294430-who-official-congo-ebola-outbreak-still-spreading-largely-undetected",
          "source": {
            "name": "Asharq Al-Awsat English"
          },
          "publishedAt": "2026-07-10T10:02:15Z",
          "image": "https://static.srpcdigital.com/styles/1200x600/public/2026-07/1657998_0.jpeg.webp",
          "language": "en"
        },
        {
          "title": "New York construction scare shows challenges of office conversions",
          "description": "The buckling of two steel columns at the former Pfizer headquarters in Manhattan has raised questions about one of the nation’s largest office-to-apartment conversions.",
          "url": "https://apnews.com/article/nyc-building-collapse-risk-pfizer-42nd-office-a2e18c24e554bcddc4989ce1c28d67d9",
          "source": {
            "name": "AP News"
          },
          "publishedAt": "2026-07-10T10:02:00Z",
          "image": "https://dims.apnews.com/dims4/default/47a6241/2147483647/strip/true/crop/3902x2600+0+0/resize/980x653!/quality/90/?url=https%3A%2F%2Fassets.apnews.com%2F86%2F99%2F31d2000053d1cd7bd6947d4319f9%2F06e039e06507466daa1c65a108155b60",
          "language": "en"
        },
        {
          "title": "Baba Barfani ice lingam melts over 90% just days into Amarnath Yatra: ‘Climate change is reason’",
          "description": "The Amarnath Yatra began on July 3 this year under unprecedented security following the April 2025 Pahalgam terror attack that killed 26 civilians. | India News",
          "url": "https://www.hindustantimes.com/india-news/baba-barfani-ice-lingam-melts-over-90-just-days-into-amarnath-yatra-climate-change-is-reason-101783674979100.html",
          "source": {
            "name": "Hindustan Times"
          },
          "publishedAt": "2026-07-10T10:01:56Z",
          "image": "https://www.hindustantimes.com/ht-img/img/2026/07/10/550x309/Lingam_1783675815964_1783675823075_bad8eb9b-9ce9-4f5c-8bc9-542cee3fc025.jpeg",
          "language": "en"
        },
        {
          "title": "Offering pure petrol, E10 not feasible; E20 fuel is superior, cleaner: Centre",
          "description": "India achieved 20% ethanol blending in petrol last year and at present, the E20 fuel is the standard petrol variant across the country.",
          "url": "https://indianexpress.com/article/business/government-rejects-e20-petrol-backlash-logistics-pure-petrol-india-10780500/",
          "source": {
            "name": "The Indian Express"
          },
          "publishedAt": "2026-07-10T10:01:15Z",
          "image": "https://images.indianexpress.com/2026/07/ethanol-implementation-order.jpg",
          "language": "en"
        },
        {
          "title": "Iran's Strait of Hormuz leverage over oil prices may be weakening",
          "description": "Iran's attacks on commercial shipping in the Strait of Hormuz sent oil prices higher, but alternative routes and OPEC+ output may be weakening Tehran's leverage.",
          "url": "https://www.foxnews.com/politics/irans-biggest-weapon-against-us-may-slipping-away-experts-say",
          "source": {
            "name": "Fox News"
          },
          "publishedAt": "2026-07-10T10:00:45Z",
          "image": "https://static.foxnews.com/foxnews.com/content/uploads/2026/07/hormuz.jpg",
          "language": "en"
        },
        {
          "title": "GitHub Copilot CLI Gets Tabs and No-Config-File Tool Setup in Redesigned Terminal UI",
          "description": "GitHub has made the redesigned GitHub Copilot CLI terminal interface generally available. It adds a tabbed layout for sessions, gists, issues, and pull requests; an in-session, form-driven setup for M",
          "url": "https://www.infoq.com/news/2026/07/copilot-cli-terminal-ga/",
          "source": {
            "name": "infoq.com"
          },
          "publishedAt": "2026-07-10T10:00:37Z",
          "image": "https://res.infoq.com/news/2026/07/copilot-cli-terminal-ga/en/headerimage/header-1783593957858.jpeg",
          "language": "en"
        },
        {
          "title": "Antidepressants Linked to Suicide Risk, Irregular Heartbeat, and Sudden Death",
          "description": "This week Mad in America examines three studies related to adverse effects of antidepressants. The first study finds that antidepressant use is linked to New research examines links between antidepressant use and self-injury in bipolar disorder, irregular heartbeat when combined with antipsychotics, and frequent side effects such as weight gain, insomnia, and sexual dysfunction.",
          "url": "https://www.madinamerica.com/2026/07/antidepressants-linked-to-suicide-risk-irregular-heartbeat-and-sudden-death/",
          "source": {
            "name": "Mad In America"
          },
          "publishedAt": "2026-07-10T10:00:27Z",
          "image": "https://www.madinamerica.com/wp-content/uploads/2026/03/WRD.jpg",
          "language": "en"
        }
      ]
    }
  }
}
